pyeventor/.DS_Store
pyeventor/__init__.py
pyeventor/aggregate.py
pyeventor/asyncio/aggregate.py
pyeventor/asyncio/event_store.py
pyeventor/decorator.py
pyeventor/event.py
pyeventor/event_store.py
pyeventor/exceptions.py
pyeventor/handler.py
pyeventor/plugins/.DS_Store
pyeventor/plugins/in_memory_store.py
pyeventor/plugins/postgres_store.py
pyeventor-1.0.dist-info/LICENSE
pyeventor-1.0.dist-info/METADATA
pyeventor-1.0.dist-info/WHEEL
pyeventor-1.0.dist-info/RECORD
